README.md
setup.py
easy_cdll.egg-info/PKG-INFO
easy_cdll.egg-info/SOURCES.txt
easy_cdll.egg-info/dependency_links.txt
easy_cdll.egg-info/top_level.txt
ezdll/__init__.py
ezdll/cstyles/__init__.py
ezdll/cstyles/cstyles.py
ezdll/tests/__init__.py
ezdll/tests/test_load_call.py