Metadata-Version: 2.1
Name: easy-cdll
Version: 0.1.1
Summary: Boost the transaction formatting and development between python and c languages
Home-page: https://github.com/techsol-ntu/easy-cdll
Author: techsol-ntu
Author-email: techsol.workspace.tmp@gmail.com
License: UNKNOWN
Platform: UNKNOWN
Classifier: Programming Language :: Python :: 3
Classifier: License :: OSI Approved :: Apache Software License
Classifier: Operating System :: OS Independent
Requires-Python: >=3.8
